wudz_perms.py
wuddz_perms-1.0.1.dist-info/METADATA
wuddz_perms-1.0.1.dist-info/WHEEL
wuddz_perms-1.0.1.dist-info/entry_points.txt
wuddz_perms-1.0.1.dist-info/licenses/LICENSE
wuddz_perms-1.0.1.dist-info/RECORD
