Metadata-Version: 2.1
Name: wuddz-perms
Version: 1.0.1
Summary: Generate All/Non-Repeat Character Permutations/Combinations Of String Or Mac Addresses With Prefix/Suffix Partial Address
Project-URL: Homepage, https://github.com/wuddz-devs/wuddz-perms
Author-email: Wuddz-Devs <wuddz_devs@protonmail.com>
License: MIT License
License-File: LICENSE
Keywords: combinations,generator,password,permutations,string
Classifier: License :: OSI Approved :: MIT License
Classifier: Programming Language :: Python
Classifier: Programming Language :: Python :: 3.7
Classifier: Programming Language :: Python :: 3.8
Classifier: Programming Language :: Python :: 3.9
Classifier: Programming Language :: Python :: 3.10
Requires-Python: >=3.7
